algebraist/__init__.py
algebraist-0.0.0.dist-info/METADATA
algebraist-0.0.0.dist-info/WHEEL
algebraist-0.0.0.dist-info/top_level.txt
algebraist-0.0.0.dist-info/RECORD
