Metadata-Version: 2.1
Name: algebraist
Version: 0.0.0
Summary: Coming soon
Author-email: Shameel Arafin <shameel@signalfive.com>
